genius_agent/__init__.py
genius_agent/agent_construct.py
genius_agent/agent_model.py
genius_agent/genius_agent_api.py
genius_agent/genius_agent_cli.py
genius_agent/prometheus_collector.py
genius_agent/version.py
genius_agent-2.11.0.dist-info/LICENSE
genius_agent-2.11.0.dist-info/METADATA
genius_agent-2.11.0.dist-info/WHEEL
genius_agent-2.11.0.dist-info/entry_points.txt
genius_agent-2.11.0.dist-info/top_level.txt
genius_agent-2.11.0.dist-info/RECORD
