Metadata-Version: 2.1
Name: genius-agent
Version: 2.11.0
Summary: Create various chat agents based off YAML or JSON files of predefined configs
Home-page: https://github.com/Knuckles-Team/genius-agent
Author: Audel Rouhi
Author-email: knucklessg1@gmail.com
Maintainer: Audel Rouhi
Maintainer-email: knucklessg1@gmail.com
License: MIT
Platform: UNKNOWN
Classifier: Development Status :: 5 - Production/Stable
Classifier: License :: Public Domain
Classifier: Environment :: Console
Classifier: Operating System :: POSIX :: Linux
Classifier: Programming Language :: Python :: 3.8
Classifier: Programming Language :: Python :: 3.9
Classifier: Programming Language :: Python :: 3.10
Classifier: Programming Language :: Python :: 3.11
Classifier: Programming Language :: Python :: 3.12
License-File: LICENSE
Requires-Dist: openai (==1.3.5)
Requires-Dist: pyautogen (==0.2.0b5)
Requires-Dist: pydantic (==2.5.2)
Provides-Extra: api
Requires-Dist: fastapi (==0.104.1) ; extra == 'api'
Requires-Dist: prometheus-fastapi-instrumentator (==6.1.0) ; extra == 'api'
Requires-Dist: uvicorn (==0.24.0) ; extra == 'api'
Provides-Extra: chromadb
Requires-Dist: chromadb (==0.4.14) ; extra == 'chromadb'
Provides-Extra: memgpt
Requires-Dist: pymemgpt (==0.2.3) ; extra == 'memgpt'
Provides-Extra: pgvector
Requires-Dist: pgvector (==0.2.3) ; extra == 'pgvector'
Provides-Extra: rag
Requires-Dist: pyautogen[retrievechat] (==0.2.0b5) ; extra == 'rag'
